{
  "contestants": [
    {
      "name": "Christos",
      "enabled": false
    },
    {
      "name": "Huub",
      "enabled": true
    },
    {
      "name": "Torben",
      "enabled": true
    },
    {
      "name": "Stepan",
      "enabled": false
    },
    {
      "name": "Osman",
      "enabled": true
    },
    {
      "name": "Victorine",
      "enabled": false
    },
    {
      "name": "Mathijs",
      "enabled": true
    },
    {
      "name": "Wilfred",
      "enabled": true
    }
  ]
}